README
setup.py
myegg/__init__.py
myegg/command_line.py
myegg.egg-info/PKG-INFO
myegg.egg-info/SOURCES.txt
myegg.egg-info/dependency_links.txt
myegg.egg-info/entry_points.txt
myegg.egg-info/not-zip-safe
myegg.egg-info/requires.txt
myegg.egg-info/top_level.txt