Metadata-Version: 1.0
Name: myegg
Version: 0.1
Summary: The hello world from myegg 
Home-page: https://github.com/huaqiangli/myegg
Author: Huaqiang Li
Author-email: huaqiangli@hotmail.com
License: MIT
Keywords: myegg egg hello world
Platform: UNKNOWN
